kerncraft/__init__.py
kerncraft/cacheprediction.py
kerncraft/cachetile.py
kerncraft/iaca.py
kerncraft/iaca_get.py
kerncraft/incore_model.py
kerncraft/intervals.py
kerncraft/kerncraft.py
kerncraft/kernel.py
kerncraft/likwid_bench_auto.py
kerncraft/machinemodel.py
kerncraft/picklemerge.py
kerncraft/prefixedunit.py
kerncraft/pycparser_utils.py
kerncraft/roofline-plot.py
kerncraft/standalone_pheno.py
kerncraft/headers/dummy.c
kerncraft/headers/kerncraft.h
kerncraft/headers/timing.c
kerncraft/headers/timing.h
kerncraft/models/__init__.py
kerncraft/models/base.py
kerncraft/models/benchmark.py
kerncraft/models/ecm.py
kerncraft/models/layer_condition.py
kerncraft/models/roofline.py
kerncraft/models/standalone_benchmark.py
kerncraft/scripts/machine-state.sh
kerncraft/symbolic/__init__.py
kerncraft/symbolic/utils.py
kerncraft-0.8.16.data/scripts/machine-state.sh
kerncraft-0.8.16.dist-info/LICENSE
kerncraft-0.8.16.dist-info/METADATA
kerncraft-0.8.16.dist-info/WHEEL
kerncraft-0.8.16.dist-info/entry_points.txt
kerncraft-0.8.16.dist-info/top_level.txt
kerncraft-0.8.16.dist-info/RECORD
