Metadata-Version: 2.1
Name: kerncraft
Version: 0.8.16
Summary: Loop Kernel Analysis and Performance Modeling Toolkit
Home-page: https://github.com/RRZE-HPC/kerncraft
Author: Julian Hammer
Author-email: julian.hammer@fau.de
License: AGPLv3
Keywords: hpc performance benchmark analysis
Classifier: Development Status :: 5 - Production/Stable
Classifier: Intended Audience :: Developers
Classifier: Intended Audience :: Science/Research
Classifier: Topic :: Scientific/Engineering
Classifier: Topic :: Software Development
Classifier: Topic :: Utilities
Classifier: License :: OSI Approved :: GNU Affero General Public License v3
Classifier: Programming Language :: Python :: 3
Classifier: Programming Language :: Python :: 3.7
Classifier: Programming Language :: Python :: 3.8
Classifier: Programming Language :: Python :: 3.9
Classifier: Programming Language :: Python :: 3.10
Requires-Python: >=3.7
License-File: LICENSE
Requires-Dist: ruamel.yaml>=0.15.37
Requires-Dist: sympy>=1.7.1
Requires-Dist: pycachesim>=0.2.3
Requires-Dist: numpy
Requires-Dist: requests
Requires-Dist: pycparser>=2.21
Requires-Dist: osaca>=0.4.0
Requires-Dist: psutil
Requires-Dist: compress-pickle
Provides-Extra: plot
Requires-Dist: matplotlib; extra == "plot"
